az_secure_env/add_env.py
az_secure_env/appservice.py
az_secure_env/azure_auth.py
az_secure_env/cli.py
az_secure_env/keyvault.py
az_secure_env/menu_helpers.py
az_secure_env/migrate.py
az_secure_env/output.py
az_secure_env/permissions.py
az_secure_env-1.0.1.dist-info/licenses/LICENSE
az_secure_env-1.0.1.dist-info/METADATA
az_secure_env-1.0.1.dist-info/WHEEL
az_secure_env-1.0.1.dist-info/entry_points.txt
az_secure_env-1.0.1.dist-info/top_level.txt
az_secure_env-1.0.1.dist-info/RECORD
