Metadata-Version: 2.4
Name: az-secure-env
Version: 1.0.1
Summary: A simple CLI tool to secure Azure App Services and Function Apps by managing environment variables safely with Azure Key Vault
Author-email: Aakash Shah <aakash.shah@simformsolutions.com>
License: MIT
Keywords: azure,keyvault,security,app-service,function-app,environment-variables,secrets
Classifier: Development Status :: 4 - Beta
Classifier: Intended Audience :: Developers
Classifier: Topic :: Security
Classifier: Topic :: System :: Systems Administration
Classifier: License :: OSI Approved :: MIT License
Classifier: Programming Language :: Python :: 3
Classifier: Programming Language :: Python :: 3.8
Classifier: Programming Language :: Python :: 3.9
Classifier: Programming Language :: Python :: 3.10
Classifier: Programming Language :: Python :: 3.11
Classifier: Programming Language :: Python :: 3.12
Requires-Python: >=3.8
License-File: LICENSE
Requires-Dist: typer
Requires-Dist: azure-identity
Requires-Dist: azure-mgmt-web
Requires-Dist: azure-keyvault-secrets
Requires-Dist: azure-mgmt-authorization
Requires-Dist: azure-mgmt-keyvault
Requires-Dist: azure-mgmt-resource
Requires-Dist: rich
Dynamic: license-file
